{
  "version": 1,
  "release_line": "0.1.0",
  "blessed_automated_e2e_count": 1,
  "warning_on_growth": true,
  "ci_fail_without_justification": false,
  "blessed_tests": [
    {
      "id": "E2E-01",
      "name": "core review happy path",
      "tier": "gated_or_nightly",
      "status": "blessed",
      "justification": "Protects the core local-first Roger review loop across provider execution, findings normalization, local approval flow, GitHub-adapter double posting, and audit persistence."
    }
  ],
  "growth_policy": {
    "requires_budget_update": true,
    "requires_written_justification": true,
    "preferred_alternatives": [
      "unit",
      "parameterized",
      "narrow_integration"
    ],
    "warning_message_style": "direct"
  }
}
